pdflator/__init__.py
pdflator/main.py
pdflator/translate_pdf.py
pdflator/web.py
pdflator/languages/__init__.py
pdflator/languages/arabic.py
pdflator/languages/english.py
pdflator/languages/french.py
pdflator/languages/language.py
pdflator/languages/turkish.py
pdflator/static/__init__.py
pdflator/static/favicon.ico
pdflator/static/logo.png
pdflator/static/css/style.css
pdflator/templates/__init__.py
pdflator/templates/config.html
pdflator/templates/history.html
pdflator/templates/index.html
pdflator/templates/result.html
pdflator/translation/__init__.py
pdflator/translation/google_translator.py
pdflator/translation/libretranslate_translator.py
pdflator/translation/translator.py
pdflator-1.0.0.dist-info/METADATA
pdflator-1.0.0.dist-info/WHEEL
pdflator-1.0.0.dist-info/entry_points.txt
pdflator-1.0.0.dist-info/top_level.txt
pdflator-1.0.0.dist-info/RECORD
