Metadata-Version: 2.4
Name: pdflator
Version: 1.0.0
Summary: A PDF translator that preserves layout
Home-page: https://github.com/bayramenes/PDFlator
Author: Enes Bayram
Author-email: enes.bayram1@proton.me
Project-URL: Bug Tracker, https://github.com/bayramenes/PDFlator/issues
Classifier: Programming Language :: Python :: 3
Classifier: License :: OSI Approved :: MIT License
Classifier: Operating System :: OS Independent
Classifier: Topic :: Office/Business
Classifier: Topic :: Utilities
Requires-Python: >=3.7
Requires-Dist: flask>=3.0.0
Requires-Dist: pymupdf>=1.22.0
Requires-Dist: pymupdf-fonts>=1.0.5
Requires-Dist: googletrans>=4.0.0
Requires-Dist: libretranslatepy>=2.1.4
Requires-Dist: python-dotenv>=1.0.0
Dynamic: author
Dynamic: author-email
Dynamic: classifier
Dynamic: description
Dynamic: description-content-type
Dynamic: home-page
Dynamic: project-url
Dynamic: requires-dist
Dynamic: requires-python
Dynamic: summary
